{
  "createdAt": "2022-12-06T00:17:41.954Z",
  "id": "747",
  "amount": 32,
  "invoiceId": "00016830",
  "paidToMerchant": false,
  "identifierNumber": 1479,
  "billingDate": "2022-12-06T00:17:41.954Z",
  "deliveryType": null,
  "channel": "IN_STORE",
  "deliveryStatus": "DELIVERED",
  "data": null,
  "downPaymentPaidAt": null,
  "status": "CLOSED",
  "paymentDetails": {
    "user": {
      "identificationNumber": "27671844",
      "fullName": "ORIANA CRISTINA BUJAICO SUAREZ",
      "phoneNumber": "+584126086556"
    },
    "installments": [
      {
        "id": "2431",
        "installmentNumber": 1,
        "scheduledPaymentDate": "2022-12-20T00:19:24.096Z",
        "amount": 5.333333333333333,
        "status": "DONE"
      },
      {
        "id": "2430",
        "installmentNumber": 0,
        "scheduledPaymentDate": "2022-12-06T00:19:24.097Z",
        "amount": 16,
        "status": "DONE"
      },
      {
        "id": "2432",
        "installmentNumber": 2,
        "scheduledPaymentDate": "2023-01-03T00:19:24.096Z",
        "amount": 5.333333333333333,
        "status": "DONE"
      },
      {
        "id": "2433",
        "installmentNumber": 3,
        "scheduledPaymentDate": "2023-01-17T00:19:24.096Z",
        "amount": 5.333333333333333,
        "status": "DONE"
      }
    ]
  },
  "store": {
    "id": 19,
    "name": "Balú Moda Sambil Chacao"
  },
  "orderProducts": [],
  "shipment": null,
  "statusName": "CLOSED"
}