{
  "createdAt": "2022-12-17T23:38:35.061Z",
  "id": "2120",
  "amount": 60.49,
  "invoiceId": "4044",
  "paidToMerchant": false,
  "identifierNumber": 2666,
  "billingDate": "2022-12-17T23:38:35.061Z",
  "deliveryType": null,
  "channel": "IN_STORE",
  "deliveryStatus": "DELIVERED",
  "data": {
    "lastPosId": "78",
    "buyDebtDate": "2023-01-31T04:00:01.539+00:00",
    "lastStoreId": 65,
    "boughtForInstallmentId": "6909",
    "boughtForInstallmentNumber": 3
  },
  "downPaymentPaidAt": null,
  "status": "CLOSED",
  "paymentDetails": {
    "user": {
      "identificationNumber": "25533134",
      "fullName": "ERNESTO ISAIAS SOSA GUEVARA",
      "phoneNumber": "+584242782121"
    },
    "installments": [
      {
        "id": "6909",
        "installmentNumber": 3,
        "scheduledPaymentDate": "2023-01-28T23:38:58.921Z",
        "amount": 10.08,
        "status": "DONE"
      },
      {
        "id": "6908",
        "installmentNumber": 2,
        "scheduledPaymentDate": "2023-01-14T23:38:58.921Z",
        "amount": 10.08,
        "status": "DONE"
      },
      {
        "id": "6907",
        "installmentNumber": 1,
        "scheduledPaymentDate": "2022-12-31T23:38:58.921Z",
        "amount": 10.08,
        "status": "DONE"
      },
      {
        "id": "6906",
        "installmentNumber": 0,
        "scheduledPaymentDate": "2022-12-17T23:38:58.921Z",
        "amount": 30.25,
        "status": "DONE"
      }
    ]
  },
  "store": {
    "id": 7,
    "name": "Cashea"
  },
  "orderProducts": [],
  "shipment": null,
  "statusName": "CLOSED"
}