{
  "createdAt": "2022-12-21T23:19:30.413Z",
  "id": "3283",
  "amount": 73.53,
  "invoiceId": "00001896",
  "paidToMerchant": false,
  "identifierNumber": 3734,
  "billingDate": "2022-12-21T23:19:30.413Z",
  "deliveryType": null,
  "channel": "IN_STORE",
  "deliveryStatus": "DELIVERED",
  "data": null,
  "downPaymentPaidAt": null,
  "status": "CLOSED",
  "paymentDetails": {
    "user": {
      "identificationNumber": "31249279",
      "fullName": "HECTOR JORDANI SOLIS GARCIA",
      "phoneNumber": "+584149142040"
    },
    "installments": [
      {
        "id": "10917",
        "installmentNumber": 3,
        "scheduledPaymentDate": "2023-02-01T23:19:43.617Z",
        "amount": 12.253333333333332,
        "status": "DONE"
      },
      {
        "id": "10914",
        "installmentNumber": 0,
        "scheduledPaymentDate": "2022-12-21T23:19:43.617Z",
        "amount": 36.77,
        "status": "DONE"
      },
      {
        "id": "10916",
        "installmentNumber": 2,
        "scheduledPaymentDate": "2023-01-18T23:19:43.617Z",
        "amount": 12.253333333333332,
        "status": "DONE"
      },
      {
        "id": "10915",
        "installmentNumber": 1,
        "scheduledPaymentDate": "2023-01-04T23:19:43.617Z",
        "amount": 12.253333333333332,
        "status": "DONE"
      }
    ]
  },
  "store": {
    "id": 39,
    "name": "Balú Moda Tolón"
  },
  "orderProducts": [],
  "shipment": null,
  "statusName": "CLOSED"
}