{
  "createdAt": "2022-12-24T21:05:15.554Z",
  "id": "4897",
  "amount": 90.74,
  "invoiceId": "7146",
  "paidToMerchant": false,
  "identifierNumber": 5138,
  "billingDate": "2022-12-24T21:05:15.554Z",
  "deliveryType": null,
  "channel": "IN_STORE",
  "deliveryStatus": "DELIVERED",
  "data": null,
  "downPaymentPaidAt": null,
  "status": "CLOSED",
  "paymentDetails": {
    "user": {
      "identificationNumber": "22965210",
      "fullName": "YVIS ROSARIO MENDOZA PAEZ",
      "phoneNumber": "+584241239855"
    },
    "installments": [
      {
        "id": "16774",
        "installmentNumber": 0,
        "scheduledPaymentDate": "2022-12-24T21:05:25.078Z",
        "amount": 45.37,
        "status": "DONE"
      },
      {
        "id": "16777",
        "installmentNumber": 3,
        "scheduledPaymentDate": "2023-02-04T21:05:25.078Z",
        "amount": 15.123333333333333,
        "status": "DONE"
      },
      {
        "id": "16776",
        "installmentNumber": 2,
        "scheduledPaymentDate": "2023-01-21T21:05:25.078Z",
        "amount": 15.123333333333333,
        "status": "DONE"
      },
      {
        "id": "16775",
        "installmentNumber": 1,
        "scheduledPaymentDate": "2023-01-07T21:05:25.078Z",
        "amount": 15.123333333333333,
        "status": "DONE"
      }
    ]
  },
  "store": {
    "id": 54,
    "name": "Balú Moda CC Lider"
  },
  "orderProducts": [],
  "shipment": null,
  "statusName": "CLOSED"
}